odoo10_addon_account_payment_order-10.0.1.7.0-py3.8-nspkg.pth
odoo/addons/account_payment_order/README.rst
odoo/addons/account_payment_order/__init__.py
odoo/addons/account_payment_order/__manifest__.py
odoo/addons/account_payment_order/data/payment_seq.xml
odoo/addons/account_payment_order/demo/payment_demo.xml
odoo/addons/account_payment_order/i18n/account_payment_order.pot
odoo/addons/account_payment_order/i18n/am.po
odoo/addons/account_payment_order/i18n/ar.po
odoo/addons/account_payment_order/i18n/ca.po
odoo/addons/account_payment_order/i18n/cs.po
odoo/addons/account_payment_order/i18n/da_DK.po
odoo/addons/account_payment_order/i18n/de.po
odoo/addons/account_payment_order/i18n/el_GR.po
odoo/addons/account_payment_order/i18n/es.po
odoo/addons/account_payment_order/i18n/es_CR.po
odoo/addons/account_payment_order/i18n/es_EC.po
odoo/addons/account_payment_order/i18n/es_ES.po
odoo/addons/account_payment_order/i18n/es_MX.po
odoo/addons/account_payment_order/i18n/es_VE.po
odoo/addons/account_payment_order/i18n/et.po
odoo/addons/account_payment_order/i18n/fi.po
odoo/addons/account_payment_order/i18n/fr.po
odoo/addons/account_payment_order/i18n/gl.po
odoo/addons/account_payment_order/i18n/hr.po
odoo/addons/account_payment_order/i18n/it.po
odoo/addons/account_payment_order/i18n/lt.po
odoo/addons/account_payment_order/i18n/nb_NO.po
odoo/addons/account_payment_order/i18n/nl.po
odoo/addons/account_payment_order/i18n/nl_BE.po
odoo/addons/account_payment_order/i18n/nl_NL.po
odoo/addons/account_payment_order/i18n/pl.po
odoo/addons/account_payment_order/i18n/pt.po
odoo/addons/account_payment_order/i18n/pt_BR.po
odoo/addons/account_payment_order/i18n/pt_PT.po
odoo/addons/account_payment_order/i18n/ro.po
odoo/addons/account_payment_order/i18n/ru.po
odoo/addons/account_payment_order/i18n/sl.po
odoo/addons/account_payment_order/i18n/th.po
odoo/addons/account_payment_order/i18n/tr.po
odoo/addons/account_payment_order/i18n/vi.po
odoo/addons/account_payment_order/models/__init__.py
odoo10_addon_account_payment_order-10.0.1.7.0.dist-info/METADATA
odoo10_addon_account_payment_order-10.0.1.7.0.dist-info/WHEEL
odoo10_addon_account_payment_order-10.0.1.7.0.dist-info/namespace_packages.txt
odoo10_addon_account_payment_order-10.0.1.7.0.dist-info/top_level.txt
odoo10_addon_account_payment_order-10.0.1.7.0.dist-info/RECORD
