Metadata-Version: 2.1
Name: odoo10-addon-account-payment-order
Version: 10.0.1.7.0
Summary: Account Payment Order
Home-page: https://github.com/OCA/bank-payment
Author: ACSONE SA/NV, Therp BV, Tecnativa, Akretion, Odoo Community Association (OCA)
Author-email: support@odoo-community.org
License: AGPL-3
Platform: UNKNOWN
Classifier: Programming Language :: Python
Classifier: Framework :: Odoo
Classifier: License :: OSI Approved :: GNU Affero General Public License v3
Requires-Python: ~=2.7
Requires-Dist: odoo10-addon-account-payment-partner
Requires-Dist: odoo (<10.1dev,>=10.0)
